Metadata-Version: 2.1
Name: dtptcpy
Version: 0.1.1
Summary: 数据交换中心 Data transportation center
Home-page: https://gitee.com/w-8
Author: bili:凿寂
Author-email: mdzzdyxc@163.com
License: MIT
Platform: UNKNOWN
Classifier: Programming Language :: Python :: 3
Classifier: License :: OSI Approved :: MIT License
Classifier: Operating System :: OS Independent
License-File: LICENSE
